MANIFEST.in
README.md
setup.py
connecty/__init__.py
connecty/__main__.py
connecty/args.py
connecty/core.py
connecty/defaults.ini
connecty/gbl.py
connecty.egg-info/PKG-INFO
connecty.egg-info/SOURCES.txt
connecty.egg-info/dependency_links.txt
connecty.egg-info/entry_points.txt
connecty.egg-info/requires.txt
connecty.egg-info/top_level.txt