Metadata-Version: 2.1
Name: connecty
Version: 2.0.5
Summary: Discord.py bot to connect channels across servers
Home-page: https://discord.gg/fcZBB2v
Author: Znunu
License: UNKNOWN
Platform: UNKNOWN
